setup.py
shinkenplugins/__init__.py
shinkenplugins.plugins.apache_server_status.egg-info/PKG-INFO
shinkenplugins.plugins.apache_server_status.egg-info/SOURCES.txt
shinkenplugins.plugins.apache_server_status.egg-info/dependency_links.txt
shinkenplugins.plugins.apache_server_status.egg-info/entry_points.txt
shinkenplugins.plugins.apache_server_status.egg-info/namespace_packages.txt
shinkenplugins.plugins.apache_server_status.egg-info/requires.txt
shinkenplugins.plugins.apache_server_status.egg-info/top_level.txt
shinkenplugins/plugins/__init__.py
shinkenplugins/plugins/apache_server_status/__init__.py
shinkenplugins/plugins/apache_server_status/apache_server_status.py