Metadata-Version: 1.0
Name: shinkenplugins.plugins.apache-server-status
Version: 1.2
Summary: Get Apache metrics from mod_status Apache status
Home-page: https://github.com/savoirfairelinux/sfl-shinken-plugins
Author: Savoir-faire Linux
Author-email: supervision@savoirfairelinux.com
License: GPL3+
Platform: any
